imgflip/__init__.py
imgflip/__main__.py
imgflip/api.py
imgflip/cli.py
imgflip/utils.py
imgflip-0.1.0.dist-info/METADATA
imgflip-0.1.0.dist-info/WHEEL
imgflip-0.1.0.dist-info/entry_points.txt
imgflip-0.1.0.dist-info/top_level.txt
imgflip-0.1.0.dist-info/RECORD
