Metadata-Version: 2.1
Name: imgflip
Version: 0.1.0
Summary: api to imgflip
Home-page: https://github.com/axju/imgflip
Author: axju
Author-email: moin@axju.de
License: UNKNOWN
Platform: UNKNOWN
Classifier: Programming Language :: Python :: 3
Classifier: License :: OSI Approved :: MIT License
Classifier: Operating System :: OS Independent
Requires-Dist: requires
